{
  "name": "AliUpgradeUI",
  "version": "1.0.0.200228103520",
  "summary": "AliUpgradeUI - 支付宝钱包AliUpgradeUI类库",
  "description": "* Detail about this framework.",
  "homepage": "http://www.alipay.com/AliUpgradeUI",
  "license": "MIT (example)",
  "authors": {
    "未定义": "undefined@alipay.com"
  },
  "platforms": {
    "ios": "5.0"
  },
  "source": {
    "http": "https://mpaas-ios.oss-cn-hangzhou.aliyuncs.com/mPaaS-SDK-Public/AliUpgradeUI/1_0_0_200228103520.tar.gz"
  },
  "preserve_paths": "AliUpgradeUI.framework/*",
  "resources": "AliUpgradeUI.framework/*.bundle",
  "vendored_frameworks": "AliUpgradeUI.framework",
  "requires_arc": true,
  "xcconfig": {
    "FRAMEWORK_SEARCH_PATHS": "$(PODS_ROOT)/AliUpgradeUI"
  }
}